flask_blogtheme.py
Flask_BlogTheme-0.2.2.dist-info/DESCRIPTION.rst
Flask_BlogTheme-0.2.2.dist-info/METADATA
Flask_BlogTheme-0.2.2.dist-info/RECORD
Flask_BlogTheme-0.2.2.dist-info/WHEEL
Flask_BlogTheme-0.2.2.dist-info/metadata.json
Flask_BlogTheme-0.2.2.dist-info/top_level.txt
