Metadata-Version: 2.0
Name: Flask-BlogTheme
Version: 0.2.2
Summary: Flask extension to read switch theme easily
Home-page: https://github.com/frostming/Flask-BlogTheme
Author: Frost Ming
Author-email: mianghong@gmail.com
License: MIT
Platform: UNKNOWN
Classifier: License :: OSI Approved :: MIT License
Classifier: Programming Language :: Python
Classifier: Programming Language :: Python :: 2.7
Classifier: Programming Language :: Python :: 3
Classifier: Programming Language :: Python :: 3.4
Classifier: Programming Language :: Python :: 3.5
Classifier: Programming Language :: Python :: 3.6
Classifier: Programming Language :: Python :: Implementation :: CPython
Classifier: Programming Language :: Python :: Implementation :: PyPy
Requires-Dist: pyyaml
